{
  "appPageId" : "1ea4cd32-d8b1-4474-918d-713544400617",
  "componentName" : "siteforce:sldsOneColLayout",
  "dataProviders" : [ ],
  "id" : "afb80bc0-519d-4fa3-9907-dccea036076f",
  "label" : "Case Related List",
  "regions" : [ {
    "id" : "758956fb-a160-4b6a-9ef9-ff987fedc580",
    "regionName" : "header",
    "type" : "region"
  }, {
    "components" : [ {
      "componentAttributes" : {
        "parentRecordId" : "{!parentRecordId}",
        "relatedListName" : "{!relatedListName}"
      },
      "componentName" : "forceCommunity:relatedList",
      "id" : "6282cc04-ca6e-4f56-966e-c61fe01e3e22",
      "renderPriority" : "NEUTRAL",
      "renditionMap" : { },
      "type" : "component"
    } ],
    "id" : "a54161c2-9203-4d80-9fe0-d62b44e1233e",
    "regionName" : "content",
    "type" : "region"
  }, {
    "components" : [ {
      "componentAttributes" : {
        "allowPrepopulatePrechatFields" : true,
        "avatarImgURL" : "",
        "defaultMinimizedText" : "Chat with Partner Assist",
        "displayHelpButton" : true,
        "eswConfigurationJSON" : {
          "baseCoreURL" : "https://ncr.my.salesforce.com",
          "baseLiveAgentContentURL" : "https://c.la4-c2-dfw.salesforceliveagent.com/content",
          "baseLiveAgentURL" : "https://d.la4-c2-dfw.salesforceliveagent.com/chat",
          "buttonId" : "5730g000000PCSq",
          "deploymentId" : "5720g0000008Ppj",
          "enabledFeatures" : [ "LiveAgent" ],
          "entryFeature" : "LiveAgent",
          "eswConfigDevName" : "IPT_Snap_In",
          "eswConfigId" : "04I0g0000008OIFEA2",
          "eswLiveAgentDevName" : "EmbeddedServiceLiveAgent_Parent04I0g0000008OIFEA2_1635352e9ce",
          "gslbBaseURL" : "https://service.force.com",
          "isOfflineCasesEnabled" : "0",
          "orgId" : "00D700000008mDk"
        },
        "externalScripts" : "",
        "externalStyles" : "",
        "fallbackRouting" : "",
        "offlineSupportMinimizedText" : "Contact Us",
        "offlineText" : "Partner Assist Offline",
        "onlineLoadingText" : "Loading",
        "prechatBackgroundImgURL" : "",
        "smallCompanyLogoImgURL" : "",
        "waitingStateBackgroundImgURL" : ""
      },
      "componentName" : "forceCommunity:embeddedService",
      "id" : "d09587ac-2905-4f61-a73e-a927058fafad",
      "renderPriority" : "NEUTRAL",
      "renditionMap" : { },
      "type" : "component"
    } ],
    "id" : "b885b27e-5070-489e-b50d-e4e991b627ed",
    "regionName" : "footer",
    "type" : "region"
  } ],
  "themeLayoutType" : "Inner",
  "type" : "view",
  "viewType" : "relatedlist-500"
}