{
  "appPageId" : "ffd493ce-e47c-4beb-8505-f4eab605a966",
  "componentName" : "siteforce:sldsOneColLayout",
  "dataProviders" : [ ],
  "id" : "23ace403-2b93-4894-acf7-e63dc58c6c2c",
  "label" : "User Related List",
  "regions" : [ {
    "id" : "c1572138-0cc9-459b-8b72-676f522474bb",
    "regionName" : "header",
    "type" : "region"
  }, {
    "components" : [ {
      "componentAttributes" : {
        "customTitle" : "",
        "parentRecordId" : "{!recordId}",
        "relatedListName" : "{!relationshipApiName}",
        "showBreadCrumbs" : true,
        "showCustomTitle" : false,
        "showManualRefreshButton" : true,
        "showRowNumbers" : true
      },
      "componentName" : "forceCommunity:relatedList",
      "id" : "6b1d677c-d338-4120-adc6-e80c16b455c6",
      "renderPriority" : "NEUTRAL",
      "renditionMap" : { },
      "type" : "component"
    } ],
    "id" : "091d3daa-6510-40b6-9b1c-e6e6f5e3199b",
    "regionName" : "content",
    "type" : "region"
  }, {
    "id" : "8ccf9c48-024e-42e3-9d7e-2ed9bafa3238",
    "regionName" : "footer",
    "type" : "region"
  } ],
  "themeLayoutType" : "Inner",
  "type" : "view",
  "viewType" : "relatedlist-005"
}