{
  "appPageId" : "37207056-b62e-4df4-a83f-a1fc32733b51",
  "componentName" : "siteforce:sldsOneColLayout",
  "dataProviders" : [ ],
  "id" : "c80b8fee-0654-4b52-9a11-87363d8f1d27",
  "label" : "Campaign Related List",
  "regions" : [ {
    "id" : "3160bbca-c379-4787-9d0c-3accb40cfe7b",
    "regionName" : "header",
    "type" : "region"
  }, {
    "components" : [ {
      "componentAttributes" : {
        "customTitle" : "",
        "parentRecordId" : "{!recordId}",
        "relatedListName" : "{!relationshipApiName}",
        "showBreadCrumbs" : true,
        "showCustomTitle" : false,
        "showManualRefreshButton" : true,
        "showRowNumbers" : true
      },
      "componentName" : "forceCommunity:relatedList",
      "id" : "4c350d43-52d9-488a-a561-d0c0dc7e348b",
      "renderPriority" : "NEUTRAL",
      "renditionMap" : { },
      "type" : "component"
    } ],
    "id" : "49d4e1ac-ad73-4d1b-be3b-2cbfb99e60bc",
    "regionName" : "content",
    "type" : "region"
  }, {
    "id" : "a594c523-67cf-407d-9fd0-6adf916ff287",
    "regionName" : "footer",
    "type" : "region"
  } ],
  "themeLayoutType" : "Inner",
  "type" : "view",
  "viewType" : "relatedlist-701"
}