{
  "appPageId" : "c6888e20-1796-4233-ab72-adac08d02f26",
  "componentName" : "siteforce:sldsOneColLayout",
  "dataProviders" : [ ],
  "id" : "fa1f58ec-f7a6-4f7e-8e99-b4e67e8111d4",
  "label" : "Dashboard Related List",
  "regions" : [ {
    "id" : "2b3f25b4-ef86-49be-ac80-f74c1ca09218",
    "regionName" : "header",
    "type" : "region"
  }, {
    "components" : [ {
      "componentAttributes" : {
        "customTitle" : "",
        "parentRecordId" : "{!recordId}",
        "relatedListName" : "{!relationshipApiName}",
        "showBreadCrumbs" : true,
        "showCustomTitle" : false,
        "showManualRefreshButton" : true,
        "showRowNumbers" : true
      },
      "componentName" : "forceCommunity:relatedList",
      "id" : "d407235e-9f0d-44bb-aab2-70c58103bb08",
      "renderPriority" : "NEUTRAL",
      "renditionMap" : { },
      "type" : "component"
    } ],
    "id" : "6bc57495-2c2f-4458-b7a0-71f0c606c73a",
    "regionName" : "content",
    "type" : "region"
  }, {
    "id" : "6172a3d6-496a-4958-acfb-5d12e8012d45",
    "regionName" : "footer",
    "type" : "region"
  } ],
  "themeLayoutType" : "Inner",
  "type" : "view",
  "viewType" : "relatedlist-01Z"
}