{
  "refresh_token_expires_in" : "0",
  "api_product_list" : "[payos-boarding, payos-channel]",
  "api_product_list_json" : [ "payos-boarding", "payos-channel" ],
  "organization_name" : "ncrstag",
  "token_type" : "BearerToken",
  "issued_at" : "1626701782171",
  "client_id" : "c900131f8abe42d39bac1cc1325c4aab",
  "access_token" : "MMq2AaodeKfHxe8jLgX5K8t6OT9R",
  "application_name" : "26485d46-aa81-4173-9b06-30ffee3cdb78",
  "scope" : "POST_SITES GET_APPLICATION POST_APPLICATION GET_SITES DEL_DEVICES GET_ORGANIZATIONS PUT_DEVICES POST_DEVICES POST_ORGANIZATIONS GET_DEVICES PUT_ORGANIZATIONS PUT_GENERAL GET_GENERAL",
  "expires_in" : "3599",
  "refresh_count" : "0",
  "status" : "approved"
}